README.rst
setup.cfg
setup.py
./__init__.py
./employee.py
./employee.xml
./quickbooks.py
./quickbooks.xml
./tryton.cfg
./tests/conftest.py
./tests/test_quickbooks_payroll.py
./view/employee_form.xml
./view/import_payroll_item_start.xml
./view/quickbooks_form.xml
./view/quickbooks_tree.xml
fio_quickbooks_payroll.egg-info/PKG-INFO
fio_quickbooks_payroll.egg-info/SOURCES.txt
fio_quickbooks_payroll.egg-info/dependency_links.txt
fio_quickbooks_payroll.egg-info/entry_points.txt
fio_quickbooks_payroll.egg-info/not-zip-safe
fio_quickbooks_payroll.egg-info/requires.txt
fio_quickbooks_payroll.egg-info/top_level.txt